MANIFEST.in
setup.py
pymaoyanfont/__init__.py
pymaoyanfont/parsefont.py
pymaoyanfont.egg-info/PKG-INFO
pymaoyanfont.egg-info/SOURCES.txt
pymaoyanfont.egg-info/dependency_links.txt
pymaoyanfont.egg-info/top_level.txt
pymaoyanfont/data/base.woff
pymaoyanfont/data/test.woff