Metadata-Version: 1.2
Name: pymaoyanfont
Version: 0.0.1
Summary: A simple parsefonttool to maoyan with python
Home-page: https://github.com/cchinm/python-spider/tree/master/practical/parsefont
Author: chinming
Author-email: chinming95@foxmail.com
Maintainer: chinming
Maintainer-email: chinming95@foxmail.com
License: BSD License
Platform: all
Classifier: Development Status :: 4 - Beta
Classifier: Operating System :: OS Independent
Classifier: Intended Audience :: Developers
Classifier: License :: OSI Approved :: BSD License
Classifier: Programming Language :: Python
Classifier: Programming Language :: Python :: Implementation
Classifier: Programming Language :: Python :: 3
Classifier: Programming Language :: Python :: 3.4
Classifier: Programming Language :: Python :: 3.5
Classifier: Programming Language :: Python :: 3.6
Classifier: Topic :: Software Development :: Libraries
